django_outbox
