Metadata-Version: 1.1
Name: django-outbox
Version: 0.5.1
Summary: Django Outbox is an app that enable you to see the emails sent by your project through the web browser.
Home-page: https://github.com/poiati/django-outbox
Author: Paulo Poiati
Author-email: paulo@poiati.com
License: MIT License
Platform: UNKNOWN
Classifier: Environment :: Web Environment
Classifier: Framework :: Django
Classifier: Intended Audience :: Developers
Classifier: License :: OSI Approved :: MIT License
Classifier: Operating System :: OS Independent
Classifier: Programming Language :: Python
Classifier: Programming Language :: Python :: 2
Classifier: Programming Language :: Python :: 2.7
Classifier: Topic :: Internet :: WWW/HTTP
Classifier: Topic :: Internet :: WWW/HTTP :: Dynamic Content
